and_or_not/__init__.py
and_or_not/main.py
and_or_not-1.3.1.dist-info/LICENSE
and_or_not-1.3.1.dist-info/METADATA
and_or_not-1.3.1.dist-info/WHEEL
and_or_not-1.3.1.dist-info/top_level.txt
and_or_not-1.3.1.dist-info/RECORD
