Metadata-Version: 2.1
Name: and-or-not
Version: 1.3.1
Summary: Python 3+ version and, or, not for python beginners
Home-page: https://github.com/Harvard90873/data_structures
Author: Harvard90873
Author-email: harvard90873@gmail.com
License: MIT
Platform: UNKNOWN
Classifier: License :: OSI Approved :: MIT License
Classifier: Programming Language :: Python :: 3.9
Classifier: Programming Language :: Python :: 3
Requires-Dist: termcolor
Requires-Dist: data-structures3x
